[	
	{"input":"近S","aliases":["5S"]},
	{"input":"2D","aliases":["足払い"]},
	{"input":"5[D]","aliases":["5D!","ためダスト","溜めダスト"]},
	{"input":"41236HS","aliases":["426HS","426","41","42","41HS","42HS"]},
	{"input":"j41236HS","aliases":["空中426HS","J426HS","j426","j41","j42","j41H","j42HS"]},
	{"input":"63214HS","aliases":["624HS","624","63","62","63HS","62HS"]},
	{"input":"j63214HS","aliases":["空中624HS","J624HS","j624","j62","j63","j62HS","j63HS"]},
	{"input":"23698HS","aliases":["268HS","268","23","26","23HS","26HS"]},
	{"input":"j23698HS","aliases":["空中268HS","J268HS","j268","j23","j26","j23HS","j26HS"]},
	{"input":"21478HS","aliases":["248HS","248","21","24","21HS","24HS"]},
	{"input":"j21478HS","aliases":["空中248HS","J248HS","j248","j21","j24","j21HS","j24HS"]},
	{"input":"69874HS","aliases":["684HS","684","69","68","69HS","68HS"]},
	{"input":"j69874HS","aliases":["空中684HS","J684HS","j684","j69","j68","j69HS","j68HS"]},
	{"input":"47896HS","aliases":["486HS","486","47","48","47HS","48HS"]},
	{"input":"j47896HS","aliases":["空中486HS","J486HS","j486","j47","j48","j47HS","j48HS"]},
	{"input":"87412HS","aliases":["842H","842","87","84","87HS","84HS"]},
	{"input":"j87412HS","aliases":["空中842H","J842H","j842","j87","j84","j87HS","j84HS"]},
	{"input":"89632HS","aliases":["862H","862","89","86","89HS","86HS"]},
	{"input":"j89632HS","aliases":["空中862H","J862H","j862","j89","j86","j89HS","j86HS"]},
	{"input":"214S Level 1","aliases":["サンダーバード","サンダーバード1","214S1"]},
	{"input":"214S Level 2","aliases":["サンダーバード2","214S2"]},
	{"input":"214S Level 3","aliases":["サンダーバード3","214S3"]},
	{"input":"236S Level 1","aliases":["スカイフィッシュ","スカイフィッシュ1"]},
	{"input":"236S Level 2","aliases":["スカイフィッシュ2"]},
	{"input":"236S Level 3","aliases":["スカイフィッシュ3"]},
	{"input":"632146P","aliases":["ダウン・ウィズ・ザ・システム","ダウン・ウィズ・ザ・システム","一回転","一回転P"]},
	{"input":"720P","aliases":["ダウン・ウィズ・ザ・システム2","二回転","二回転P"]},
	{"input":"1080P","aliases":["ダウン・ウィズ・ザ・システム3","三回転","三回転P"]},
	{"input":"236236K Level 1","aliases":["バーン・イット・ダウン","バーン・イット・ダウン1"]},
	{"input":"236236K Level 2","aliases":["バーン・イット・ダウン2"]},
	{"input":"236236K Level 3","aliases":["バーン・イット・ダウン3"]},
	{"input":"6D or 4D","aliases":["投げ","6D","4D"]},
	{"input":"j6D or j4D","aliases":["空投げ","J6D","J4D"]},
	{"input":"236D","aliases":["ワイルドアサルト","WA"]},
	{"input":"236[D]","aliases":["溜めワイルドアサルト","WAH","WA!","236D!"]}
]
