[	
	{"input":"近S","aliases":["cs","5S"]},
	{"input":"2D","aliases":["足払い"]},
	{"input":"5[D]","aliases":["5D!","ためダスト","溜めダスト"]},
	{"input":"236P","aliases":["ガンフレイム","GF"]},
	{"input":"214P","aliases":["ガンフレイムフェイント","GFF"]},
	{"input":"623S","aliases":["ヴォルカニックファイパー","S ヴォルカニックファイパー","VV","SVV"]},
	{"input":"623HS","aliases":["HSヴォルカニックヴァイパー","HSVV"]},
	{"input":"j623S","aliases":["空中ヴォルカニックヴァイパー","JVV"]},
	{"input":"j623HS","aliases":["空中HSヴォルカニックヴァイパー","JHSVV"]},
	{"input":"236K","aliases":["バンディットリボルバー","バンディットリボルバー1","BR","BR1"]},
	{"input":"236KK","aliases":["バンディットリボルバー2","Bandit Revolver 2","BR2"]},
	{"input":"j236K","aliases":["空中バンディットリボルバー","空中バンディットリボルバー1","JBR","JBR1"]},
	{"input":"j236KK","aliases":["空中バンディットリボルバー2","JBR2"]},
	{"input":"214K","aliases":["バンディットブリンガー","BB"]},
	{"input":"j214K","aliases":["空中バンディットブリンガー","JBB"]},
	{"input":"623K","aliases":["ぶっきらぼうに投げる"]},
	{"input":"214S","aliases":["ヴォルテックス","NV"]},
	{"input":"41236HS","aliases":["ファフニール","ファフ"]},
	{"input":"63214HS","aliases":["タイラン","632146HS"]},
	{"input":"214214HS","aliases":["ヘヴィモブセメタリー", "ヘヴィモブ"]},
	{"input":"6D or 4D","aliases":["投げ","6D","4D"]},
	{"input":"j6D or j.4D","aliases":["空投げ","J6D","J4D"]},
	{"input":"236D","aliases":["ワイルドアサルト", "ワサルト", "WA"]},
        {"input":"236[D]","aliases":["溜めワイルドアサルト","WA!","236D!"]}
]
